obp_python/__init__.py
obp_python/addCardAttribute.py
obp_python/addFx.py
obp_python/addRole.py
obp_python/addUser.py
obp_python/answerConsent.py
obp_python/answerTransactionChallenge.py
obp_python/auth_direct_login.py
obp_python/branch-import.py
obp_python/cli.py
obp_python/createAccount.py
obp_python/createBank.py
obp_python/createCard.py
obp_python/createConsent.py
obp_python/createCustomer.py
obp_python/createHistoricalTransaction.py
obp_python/createTransaction.py
obp_python/createUser.py
obp_python/createView.py
obp_python/customAPICall.py
obp_python/deleteBranches.py
obp_python/deleteCardById.py
obp_python/deleteCards.py
obp_python/deleteView.py
obp_python/delete_branches.py
obp_python/dms_convert.py
obp_python/getAccount.py
obp_python/getAccountTransactions.py
obp_python/getAccountsHeld.py
obp_python/getBanks.py
obp_python/getCardByCardNumber.py
obp_python/getCardById.py
obp_python/getCardIdByCardNumber.py
obp_python/getCards.py
obp_python/getConsentStatus.py
obp_python/getConsents.py
obp_python/getCustomerIdByCustomerNumber.py
obp_python/getCustomers.py
obp_python/getEntitlementsCurrentUser.py
obp_python/getUserId.py
obp_python/getUserIdByUsername.py
obp_python/getUsers.py
obp_python/getViews.py
obp_python/hasEntitlements.py
obp_python/importAccounts.py
obp_python/importBranches.py
obp_python/importCardAttributes.py
obp_python/importCards.py
obp_python/importCustomers.py
obp_python/importFx.py
obp_python/importTransactions.py
obp_python/importUsers.py
obp_python/init.py
obp_python/linkUserToCustomer.py
obp_python/revokeConsent.py
obp_python/sandboxImport.py
obp_python/updateCustomerGeneralData.py
obp_python/updateCustomerNumber.py
obp_python-0.206.data/data/obp_python/sandbox/example_import.json
obp_python-0.206.dist-info/LICENSE
obp_python-0.206.dist-info/METADATA
obp_python-0.206.dist-info/WHEEL
obp_python-0.206.dist-info/entry_points.txt
obp_python-0.206.dist-info/top_level.txt
obp_python-0.206.dist-info/RECORD
