Metadata-Version: 2.1
Name: obp-python
Version: 0.206
Summary: Beta Open Bank Project Python Utilities
Home-page: https://github.com/chrisjsimpson/open-bank-project-python
Author: 
Author-email: 
License: UNKNOWN
Platform: UNKNOWN
Classifier: Programming Language :: Python :: 3
Classifier: License :: OSI Approved :: GNU General Public License v3 or later (GPLv3+)
Classifier: Operating System :: OS Independent
Requires-Python: >=3
Requires-Dist: click
Requires-Dist: requests
Requires-Dist: appdirs
Requires-Dist: dms2dec
Requires-Dist: pyexcel-ods
Requires-Dist: fx2obp (==0.2)
